cligenius-0.12.3.dist-info/METADATA
cligenius-0.12.3.dist-info/WHEEL
cligenius-0.12.3.dist-info/entry_points.txt
cligenius-0.12.3.dist-info/licenses/LICENSE
cligenius/__init__.py
cligenius/__main__.py
cligenius/_completion_classes.py
cligenius/_completion_shared.py
cligenius/_typing.py
cligenius/cli.py
cligenius/colors.py
cligenius/completion.py
cligenius/core.py
cligenius/main.py
cligenius/models.py
cligenius/params.py
cligenius/py.typed
cligenius/rich_utils.py
cligenius/testing.py
cligenius/utils.py
cligenius-0.12.3.dist-info/RECORD
