Metadata-Version: 2.1
Name: cligenius
Version: 0.12.3
Summary: Cligenius, build great CLIs. Easy to code. Based on Python type hints.
Home-page: https://github.com/khulnasoft/cligenius
Author-Email: KhulnaSoft DevOps <info@khulnasoft.com>
Classifier: Intended Audience :: Information Technology
Classifier: Intended Audience :: System Administrators
Classifier: Operating System :: OS Independent
Classifier: Programming Language :: Python :: 3
Classifier: Programming Language :: Python
Classifier: Topic :: Software Development :: Libraries :: Application Frameworks
Classifier: Topic :: Software Development :: Libraries :: Python Modules
Classifier: Topic :: Software Development :: Libraries
Classifier: Topic :: Software Development
Classifier: Typing :: Typed
Classifier: Development Status :: 4 - Beta
Classifier: Intended Audience :: Developers
Classifier: Programming Language :: Python :: 3 :: Only
Classifier: Programming Language :: Python :: 3.7
Classifier: Programming Language :: Python :: 3.8
Classifier: Programming Language :: Python :: 3.9
Classifier: Programming Language :: Python :: 3.10
Classifier: Programming Language :: Python :: 3.11
Classifier: License :: OSI Approved :: MIT License
Project-URL: Documentation, https://cligenius.khulnasoft.com/
Project-URL: Homepage, https://github.com/khulnasoft/cligenius
Requires-Python: >=3.7
Requires-Dist: click>=8.0.0
Requires-Dist: typing-extensions>=3.7.4.3
Requires-Dist: shellingham>=1.3.0
Requires-Dist: rich>=10.11.0
